{
  "chiplets": [
    {
      "name": "A",
      "x-position": 280.0,
      "y-position": 51.5,
      "width": 26.0,
      "height": 27.0,
      "rotation": 0,
      "power": 58.0
    },
    {
      "name": "B",
      "x-position": 366.0,
      "y-position": 1.0,
      "width": 12.0,
      "height": 13.0,
      "rotation": 1,
      "power": 183.0
    },
    {
      "name": "C",
      "x-position": 336.0,
      "y-position": 57.0,
      "width": 25.0,
      "height": 20.0,
      "rotation": 0,
      "power": 115.0
    },
    {
      "name": "D",
      "x-position": 305.0,
      "y-position": 13.5,
      "width": 14.0,
      "height": 17.0,
      "rotation": 0,
      "power": 19.0
    },
    {
      "name": "E",
      "x-position": 391.0,
      "y-position": 31.5,
      "width": 17.0,
      "height": 19.0,
      "rotation": 1,
      "power": 147.0
    },
    {
      "name": "F",
      "x-position": 349.0,
      "y-position": 8.0,
      "width": 17.0,
      "height": 19.0,
      "rotation": 0,
      "power": 13.0
    },
    {
      "name": "G",
      "x-position": 319.0,
      "y-position": 0.0,
      "width": 30.0,
      "height": 27.0,
      "rotation": 1,
      "power": 84.0
    },
    {
      "name": "H",
      "x-position": 378.0,
      "y-position": 1.0,
      "width": 27.0,
      "height": 27.0,
      "rotation": 0,
      "power": 174.0
    },
    {
      "name": "I",
      "x-position": 280.0,
      "y-position": 0.5,
      "width": 25.0,
      "height": 26.0,
      "rotation": 1,
      "power": 184.0
    },
    {
      "name": "J",
      "x-position": 368.5,
      "y-position": 14.0,
      "width": 7.0,
      "height": 6.0,
      "rotation": 1,
      "power": 161.0
    },
    {
      "name": "K",
      "x-position": 343.0,
      "y-position": 27.0,
      "width": 24.0,
      "height": 29.0,
      "rotation": 0,
      "power": 52.0
    },
    {
      "name": "L",
      "x-position": 367.0,
      "y-position": 28.0,
      "width": 24.0,
      "height": 26.0,
      "rotation": 0,
      "power": 37.0
    },
    {
      "name": "M",
      "x-position": 306.0,
      "y-position": 53.0,
      "width": 30.0,
      "height": 26.0,
      "rotation": 1,
      "power": 115.0
    },
    {
      "name": "N",
      "x-position": 321.0,
      "y-position": 27.0,
      "width": 22.0,
      "height": 26.0,
      "rotation": 0,
      "power": 179.0
    },
    {
      "name": "O",
      "x-position": 280.0,
      "y-position": 26.5,
      "width": 24.0,
      "height": 25.0,
      "rotation": 0,
      "power": 186.0
    },
    {
      "name": "P",
      "x-position": 383.0,
      "y-position": 54.0,
      "width": 20.0,
      "height": 25.0,
      "rotation": 0,
      "power": 150.0
    },
    {
      "name": "Q",
      "x-position": 361.0,
      "y-position": 56.0,
      "width": 22.0,
      "height": 22.0,
      "rotation": 0,
      "power": 79.0
    },
    {
      "name": "R",
      "x-position": 367.0,
      "y-position": 20.0,
      "width": 10.0,
      "height": 8.0,
      "rotation": 1,
      "power": 5.0
    },
    {
      "name": "S",
      "x-position": 304.0,
      "y-position": 30.5,
      "width": 17.0,
      "height": 21.0,
      "rotation": 1,
      "power": 183.0
    }
  ],
  "connections": [],
  "wirelength": 1403584.0,
  "area": 10112.0,
  "aspect_ratio": 0.617
}