{
  "chiplets": [
    {
      "name": "A",
      "x-position": 92.5,
      "y-position": 24.0,
      "width": 13.0,
      "height": 14.0,
      "rotation": 1,
      "power": 6.0
    },
    {
      "name": "B",
      "x-position": 40.5,
      "y-position": 2.0,
      "width": 26.0,
      "height": 22.0,
      "rotation": 1,
      "power": 93.0
    },
    {
      "name": "C",
      "x-position": 29.0,
      "y-position": 46.0,
      "width": 5.0,
      "height": 4.0,
      "rotation": 0,
      "power": 111.0
    },
    {
      "name": "D",
      "x-position": 18.0,
      "y-position": 24.0,
      "width": 11.0,
      "height": 9.0,
      "rotation": 1,
      "power": 82.0
    },
    {
      "name": "E",
      "x-position": 0.0,
      "y-position": 33.0,
      "width": 29.0,
      "height": 30.0,
      "rotation": 0,
      "power": 4.0
    },
    {
      "name": "F",
      "x-position": 18.0,
      "y-position": 63.0,
      "width": 11.0,
      "height": 10.0,
      "rotation": 1,
      "power": 5.0
    },
    {
      "name": "G",
      "x-position": 29.0,
      "y-position": 25.0,
      "width": 16.0,
      "height": 19.0,
      "rotation": 0,
      "power": 8.0
    },
    {
      "name": "H",
      "x-position": 29.0,
      "y-position": 50.0,
      "width": 19.0,
      "height": 22.0,
      "rotation": 0,
      "power": 54.0
    },
    {
      "name": "I",
      "x-position": 15.5,
      "y-position": 73.0,
      "width": 25.0,
      "height": 26.0,
      "rotation": 1,
      "power": 170.0
    },
    {
      "name": "J",
      "x-position": 45.0,
      "y-position": 24.0,
      "width": 25.0,
      "height": 26.0,
      "rotation": 1,
      "power": 74.0
    },
    {
      "name": "K",
      "x-position": 66.5,
      "y-position": 50.0,
      "width": 26.0,
      "height": 23.0,
      "rotation": 0,
      "power": 7.0
    },
    {
      "name": "L",
      "x-position": 13.5,
      "y-position": 0.0,
      "width": 27.0,
      "height": 24.0,
      "rotation": 1,
      "power": 169.0
    },
    {
      "name": "M",
      "x-position": 70.0,
      "y-position": 25.0,
      "width": 19.0,
      "height": 21.0,
      "rotation": 1,
      "power": 169.0
    },
    {
      "name": "N",
      "x-position": 70.0,
      "y-position": 8.0,
      "width": 19.0,
      "height": 17.0,
      "rotation": 1,
      "power": 41.0
    }
  ],
  "connections": [],
  "wirelength": 1000768.0,
  "area": 10444.5,
  "aspect_ratio": 0.938
}