{
  "chiplets": [
    {
      "name": "A",
      "x-position": 26.0,
      "y-position": 0.0,
      "width": 20.0,
      "height": 21.0,
      "rotation": 1,
      "power": 111.0
    },
    {
      "name": "B",
      "x-position": 49.0,
      "y-position": 0.0,
      "width": 24.0,
      "height": 25.0,
      "rotation": 1,
      "power": 10.0
    },
    {
      "name": "C",
      "x-position": 49.0,
      "y-position": 25.0,
      "width": 29.0,
      "height": 25.0,
      "rotation": 1,
      "power": 152.0
    },
    {
      "name": "D",
      "x-position": 0.0,
      "y-position": 0.0,
      "width": 13.0,
      "height": 14.0,
      "rotation": 0,
      "power": 116.0
    },
    {
      "name": "E",
      "x-position": 19.0,
      "y-position": 21.0,
      "width": 30.0,
      "height": 25.0,
      "rotation": 0,
      "power": 111.0
    },
    {
      "name": "F",
      "x-position": 0.0,
      "y-position": 14.0,
      "width": 12.0,
      "height": 15.0,
      "rotation": 1,
      "power": 100.0
    },
    {
      "name": "G",
      "x-position": 0.0,
      "y-position": 29.0,
      "width": 9.0,
      "height": 8.0,
      "rotation": 0,
      "power": 61.0
    },
    {
      "name": "H",
      "x-position": 13.0,
      "y-position": 0.0,
      "width": 13.0,
      "height": 16.0,
      "rotation": 1,
      "power": 93.0
    },
    {
      "name": "I",
      "x-position": 0.0,
      "y-position": 37.0,
      "width": 19.0,
      "height": 18.0,
      "rotation": 1,
      "power": 68.0
    }
  ],
  "connections": [],
  "wirelength": 260416.0,
  "area": 4290.0,
  "aspect_ratio": 0.705
}