{
  "chiplets": [
    {
      "name": "A",
      "x-position": 107.0,
      "y-position": 342.0,
      "width": 21.0,
      "height": 22.0,
      "rotation": 0,
      "power": 93.0
    },
    {
      "name": "B",
      "x-position": 106.0,
      "y-position": 318.0,
      "width": 22.0,
      "height": 24.0,
      "rotation": 0,
      "power": 124.0
    },
    {
      "name": "C",
      "x-position": 49.0,
      "y-position": 348.0,
      "width": 20.0,
      "height": 21.0,
      "rotation": 0,
      "power": 74.0
    },
    {
      "name": "D",
      "x-position": 0.0,
      "y-position": 344.0,
      "width": 28.0,
      "height": 29.0,
      "rotation": 0,
      "power": 94.0
    },
    {
      "name": "E",
      "x-position": 69.0,
      "y-position": 345.5,
      "width": 22.0,
      "height": 26.0,
      "rotation": 1,
      "power": 69.0
    },
    {
      "name": "F",
      "x-position": 62.0,
      "y-position": 324.5,
      "width": 21.0,
      "height": 21.0,
      "rotation": 0,
      "power": 31.0
    },
    {
      "name": "G",
      "x-position": 54.5,
      "y-position": 387.0,
      "width": 9.0,
      "height": 8.0,
      "rotation": 1,
      "power": 32.0
    },
    {
      "name": "H",
      "x-position": 91.0,
      "y-position": 345.0,
      "width": 16.0,
      "height": 19.0,
      "rotation": 0,
      "power": 16.0
    },
    {
      "name": "I",
      "x-position": 93.0,
      "y-position": 369.0,
      "width": 3.0,
      "height": 3.0,
      "rotation": 0,
      "power": 156.0
    },
    {
      "name": "J",
      "x-position": 28.0,
      "y-position": 348.0,
      "width": 21.0,
      "height": 23.0,
      "rotation": 0,
      "power": 111.0
    },
    {
      "name": "K",
      "x-position": 0.0,
      "y-position": 373.0,
      "width": 22.0,
      "height": 20.0,
      "rotation": 1,
      "power": 183.0
    },
    {
      "name": "L",
      "x-position": 50.0,
      "y-position": 369.0,
      "width": 17.0,
      "height": 18.0,
      "rotation": 0,
      "power": 143.0
    },
    {
      "name": "M",
      "x-position": 35.0,
      "y-position": 321.0,
      "width": 27.0,
      "height": 27.0,
      "rotation": 0,
      "power": 53.0
    },
    {
      "name": "N",
      "x-position": 96.0,
      "y-position": 381.0,
      "width": 15.0,
      "height": 14.0,
      "rotation": 0,
      "power": 162.0
    },
    {
      "name": "O",
      "x-position": 22.0,
      "y-position": 373.0,
      "width": 28.0,
      "height": 23.0,
      "rotation": 0,
      "power": 123.0
    },
    {
      "name": "P",
      "x-position": 8.0,
      "y-position": 318.0,
      "width": 27.0,
      "height": 26.0,
      "rotation": 0,
      "power": 144.0
    },
    {
      "name": "Q",
      "x-position": 67.0,
      "y-position": 372.0,
      "width": 29.0,
      "height": 24.0,
      "rotation": 0,
      "power": 99.0
    },
    {
      "name": "R",
      "x-position": 91.0,
      "y-position": 364.0,
      "width": 5.0,
      "height": 5.0,
      "rotation": 0,
      "power": 75.0
    },
    {
      "name": "S",
      "x-position": 83.0,
      "y-position": 326.0,
      "width": 23.0,
      "height": 19.0,
      "rotation": 1,
      "power": 90.0
    },
    {
      "name": "T",
      "x-position": 96.0,
      "y-position": 364.0,
      "width": 19.0,
      "height": 17.0,
      "rotation": 1,
      "power": 6.0
    }
  ],
  "connections": [],
  "wirelength": 1238976.0,
  "area": 9984.0,
  "aspect_ratio": 0.609
}