{
  "chiplets": [
    {
      "name": "A",
      "x-position": 1.5,
      "y-position": 16.0,
      "width": 27.0,
      "height": 26.0,
      "rotation": 0,
      "power": 36.0
    },
    {
      "name": "B",
      "x-position": 5.5,
      "y-position": 0.0,
      "width": 19.0,
      "height": 16.0,
      "rotation": 0,
      "power": 178.0
    },
    {
      "name": "C",
      "x-position": 0.0,
      "y-position": 42.0,
      "width": 30.0,
      "height": 29.0,
      "rotation": 1,
      "power": 44.0
    },
    {
      "name": "D",
      "x-position": 2.5,
      "y-position": 71.0,
      "width": 25.0,
      "height": 30.0,
      "rotation": 1,
      "power": 197.0
    }
  ],
  "connections": [],
  "wirelength": 39936.0,
  "area": 3030.0,
  "aspect_ratio": 0.297
}